.gitignore
COPYING
MANIFEST.in
README.md
setup.py
dwpwg/__init__.py
dwpwg/__main__.py
dwpwg/format.py
dwpwg/pwgen.py
dwpwg/wordlist.py
dwpwg.egg-info/PKG-INFO
dwpwg.egg-info/SOURCES.txt
dwpwg.egg-info/dependency_links.txt
dwpwg.egg-info/entry_points.txt
dwpwg.egg-info/requires.txt
dwpwg.egg-info/top_level.txt
dwpwg/lists/__init__.py
dwpwg/lists/en/full