Metadata-Version: 1.1
Name: dwpwg
Version: 0.0.2
Summary: (d)ice(w)are (p)ass(w)ord (g)enerator
Home-page: https://github.com/raspberryaether/dwpwg
Author: Raspberry Aether
Author-email: raspberryaether@riseup.net
License: UNKNOWN
Keywords: diceware,password,passwords,passphrase,passphrases,security,bitcoins,monero,crypto,cryptocurrency,key,keys,keyphrase,keyphrases,encryption,nsa,surveillance,privacy,private,secret,secrecy,generate,generator,dice,d20,brainwallet,wallet
Platform: UNKNOWN
Classifier: Development Status :: 3 - Alpha
Classifier: Environment :: Console
Classifier: License :: OSI Approved :: GNU General Public License v2 (GPLv2)
Classifier: Natural Language :: English
Classifier: Programming Language :: Python :: 2
Classifier: Programming Language :: Python :: 2.7
Classifier: Topic :: Security
Classifier: Topic :: Security :: Cryptography
Classifier: Topic :: Utilities
